odoo/addons/sm_partago_db/__init__.py
odoo/addons/sm_partago_db/__manifest__.py
odoo/addons/sm_partago_db/models/__init__.py
odoo/addons/sm_partago_db/models/models_smp_billing_account.py
odoo/addons/sm_partago_db/models/models_smp_car.py
odoo/addons/sm_partago_db/models/models_smp_car_config.py
odoo/addons/sm_partago_db/models/models_smp_db_utils.py
odoo/addons/sm_partago_db/models/models_smp_db_wizard.py
odoo/addons/sm_partago_db/models/models_smp_group.py
odoo/addons/sm_partago_db/models/models_smp_group_config.py
odoo/addons/sm_partago_db/security/ir.model.access.csv
odoo/addons/sm_partago_db/views/views.xml
odoo/addons/sm_partago_db/views/views_billing_account.xml
odoo/addons/sm_partago_db/views/views_car.xml
odoo/addons/sm_partago_db/views/views_car_config.xml
odoo/addons/sm_partago_db/views/views_group.xml
odoo/addons/sm_partago_db/views/views_group_config.xml
odoo/addons/sm_partago_db/views/views_wizards.xml
odoo11_addon_sm_partago_db-11.0.0.0.2.dist-info/METADATA
odoo11_addon_sm_partago_db-11.0.0.0.2.dist-info/WHEEL
odoo11_addon_sm_partago_db-11.0.0.0.2.dist-info/top_level.txt
odoo11_addon_sm_partago_db-11.0.0.0.2.dist-info/RECORD
